{
  "id": "1647602",
  "name": "p'm's'b",
  "font_family": "iconfont",
  "css_prefix_text": "icon-",
  "description": "",
  "glyphs": [
    {
      "icon_id": "3764366",
      "name": "预定",
      "font_class": "weibiaoti-",
      "unicode": "e615",
      "unicode_decimal": 58901
    },
    {
      "icon_id": "4337879",
      "name": "人员登记",
      "font_class": "renyuandengji",
      "unicode": "e700",
      "unicode_decimal": 59136
    },
    {
      "icon_id": "4838236",
      "name": "公安",
      "font_class": "gongan",
      "unicode": "e617",
      "unicode_decimal": 58903
    },
    {
      "icon_id": "8634404",
      "name": "制卡",
      "font_class": "zhiqia",
      "unicode": "e600",
      "unicode_decimal": 58880
    }
  ]
}
